enc_app/__init__.py
enc_app/encrypt.py
encryption_jsv-0.1.2.dist-info/METADATA
encryption_jsv-0.1.2.dist-info/WHEEL
encryption_jsv-0.1.2.dist-info/entry_points.txt
encryption_jsv-0.1.2.dist-info/top_level.txt
encryption_jsv-0.1.2.dist-info/RECORD
